badgequest/__init__.py
badgequest/app.py
badgequest/badges.py
badgequest/cli.py
badgequest/config.py
badgequest/microcredentials.py
badgequest/models.py
badgequest/similarity.py
badgequest/validators.py
badge_quest-0.3.3.dist-info/METADATA
badge_quest-0.3.3.dist-info/WHEEL
badge_quest-0.3.3.dist-info/entry_points.txt
badge_quest-0.3.3.dist-info/licenses/LICENSE
badge_quest-0.3.3.dist-info/RECORD
