Metadata-Version: 2.4
Name: badge-quest
Version: 0.3.3
Summary: Collect, learn, repeat. A reflection badge system for Learning Management Systems.
Project-URL: Homepage, https://github.com/michael-borck/badge-quest
Project-URL: Documentation, https://github.com/michael-borck/badge-quest/tree/main/docs
Project-URL: Repository, https://github.com/michael-borck/badge-quest
Project-URL: Issues, https://github.com/michael-borck/badge-quest/issues
Author-email: Michael <michael@example.com>
License: MIT
License-File: LICENSE
Keywords: badges,blackboard,education,gamification,lms,reflection
Classifier: Development Status :: 3 - Alpha
Classifier: Framework :: Flask
Classifier: Intended Audience :: Education
Classifier: License :: OSI Approved :: MIT License
Classifier: Programming Language :: Python :: 3
Classifier: Programming Language :: Python :: 3.10
Classifier: Programming Language :: Python :: 3.11
Classifier: Programming Language :: Python :: 3.12
Classifier: Topic :: Education
Requires-Python: >=3.10
Requires-Dist: click>=8.1.0
Requires-Dist: flask-cors>=4.0.0
Requires-Dist: flask>=3.0.0
Requires-Dist: python-dotenv>=1.0.0
Requires-Dist: python-levenshtein>=0.20.0
Requires-Dist: requests>=2.31.0
Requires-Dist: textblob>=0.17.1
Requires-Dist: textstat>=0.7.3
Provides-Extra: dev
Requires-Dist: basedpyright>=1.0.0; extra == 'dev'
Requires-Dist: pytest-cov>=4.1.0; extra == 'dev'
Requires-Dist: pytest>=7.4.0; extra == 'dev'
Requires-Dist: ruff>=0.1.0; extra == 'dev'
